<?xml version="1.0" encoding="UTF-8" standalone="no"?>
<item>
	<coreAttributes>
		<value>500</value> 
		<determiner><![CDATA[a vial of]]></determiner>
		<name><![CDATA[slerm slime]]></name>
		<namePlural pluralByDefault="false"><![CDATA[Slerm Slimes]]></namePlural>
		<description><![CDATA[A small vial, containing slerm slime. Whilst not particularly nice to consume, it is extremely transformative. Luckily as a safety precaution, you have to enchant it for its transformative capabilities to take effect.]]></description> 

		<useDescriptor>drink</useDescriptor>

		<sexUse>true</sexUse>
		<combatUseAllies>true</combatUseAllies>
		<combatUseEnemies>false</combatUseEnemies>
		<consumedOnUse>true</consumedOnUse>

		<rarity>RARE</rarity> 

		<imageName zLayer="0" imageRotation="0" imageSize="100">background_bottom.svg</imageName>
		<imageName zLayer="1" imageRotation="0" imageSize="90" target1='stroke="#000"' replacement1='stroke="#ff5555"' target2='#ff8080' replacement2='#ff5555'>res/mods/silverinc/race/slerm/subspecies/icon.svg</imageName>
		<imageName zLayer="2" imageRotation="0" imageSize="100">slerm_vial.svg</imageName>
		<imageName zLayer="3" imageRotation="0" imageSize="100">background_top.svg</imageName>

		<colourPrimary>BASE_GREEN_DARK</colourPrimary>
		<colourSecondary/>
		<colourTertiary/>

		<potionDescriptor><![CDATA[slerm]]></potionDescriptor>
		<associatedRace>silverinc_slerm</associatedRace>
		<enchantmentItemTypeId>ELIXIR</enchantmentItemTypeId>
		<enchantmentEffectId>RACE</enchantmentEffectId>

		<effectTooltipLines>
			<line><![CDATA[[style.boldGood(Restores)] 30% [style.boldHealth([#ATTRIBUTE_HEALTH_MAXIMUM.getName()])]]]></line>
		</effectTooltipLines>

		<applyEffects><![CDATA[
			[##npc.incrementHealth(npc.getAttributeValue(ATTRIBUTE_HEALTH_MAXIMUM)/2)]
			<p style='margin-bottom:0; padding-bottom:0;'>
				[npc.Name] [npc.verb(feel)] [npc.her] injuries start to heal...
			</p>
		]]></applyEffects>

		<itemTags>
			<tag>RACIAL_TF_ITEM</tag>
			<tag>SOLD_BY_RALPH</tag>
		</itemTags>
	</coreAttributes>

	<useDescriptions>
		<selfUse><![CDATA[
		[npc.Name] [npc.verb(open)] the vial of slerm slime and [npc.verb(look)] at its contents in a disgusted manner, the smell makes you heave. [npc.She] then [npc.verb(brace)] [npc.her]self and [npc.verb(swallow)] the contents in one,  which almost caused [npc2.her] to throw-up in [npc2.her] mouth.
		]]></selfUse>
		<otherUse><![CDATA[
		[npc.Name] [npc.verb(open)] the vial of slermslime and [npc.verb(hold)] it out to [npc2.name], allowing [npc2.herHim] to see the contents. Reluctantly, [npc2.she] then [npc2.verb(brace)] [npc2.her]self and [npc2.verb(swallow)] the contents in one, which almost caused [npc2.her] to throw-up in [npc2.her] mouth.
		]]></otherUse>
	</useDescriptions>
</item>
